sabac/PAP.py
sabac/PDP.py
sabac/PEP.py
sabac/PIP.py
sabac/__init__.py
sabac/action.py
sabac/algorithm.py
sabac/constants.py
sabac/policy.py
sabac/policy_element.py
sabac/policy_set.py
sabac/request.py
sabac/response.py
sabac/rule.py
sabac-0.0.1a0.dist-info/LICENSE.txt
sabac-0.0.1a0.dist-info/METADATA
sabac-0.0.1a0.dist-info/WHEEL
sabac-0.0.1a0.dist-info/top_level.txt
sabac-0.0.1a0.dist-info/RECORD
