Metadata-Version: 2.1
Name: sabac
Version: 0.0.1a0
Summary: Simple Attribute Based Access Control
Home-page: https://github.com/PetrovskYYY/SABAC
Author: Yuriy Petrovskiy
Author-email: yuriy.petrovskiy@gmail.com
License: UNKNOWN
Platform: UNKNOWN
Classifier: Programming Language :: Python :: 3
Classifier: License :: OSI Approved :: GNU Lesser General Public License v3 (LGPLv3)
Classifier: Operating System :: OS Independent
Requires-Python: >=3.6
